todoist_tree/__init__.py
todoist_tree/headers.py
todoist_tree/py.typed
todoist_tree/read_changes.py
todoist_tree/task_subsets.py
todoist_tree/tree.py
todoist_tree/write_changes.py
todoist_tree-0.4.0.dist-info/METADATA
todoist_tree-0.4.0.dist-info/WHEEL
todoist_tree-0.4.0.dist-info/RECORD
