Metadata-Version: 2.1
Name: todoist-tree
Version: 0.4.0
Summary: Create a tree from Todoist projects > sections > tasks
Author: Shay Hill
Author-email: shay_public@hotmail.com
Requires-Python: >=3.10,<4.0
Classifier: Programming Language :: Python :: 3
Classifier: Programming Language :: Python :: 3.10
Classifier: Programming Language :: Python :: 3.11
Requires-Dist: pydantic (>=1.10.4,<2.0.0)
Requires-Dist: requests (>=2.28.2,<3.0.0)
